routemaster_statsd/__init__.py
routemaster_statsd-1.5.0.dist-info/METADATA
routemaster_statsd-1.5.0.dist-info/WHEEL
routemaster_statsd-1.5.0.dist-info/top_level.txt
routemaster_statsd-1.5.0.dist-info/RECORD
