Metadata-Version: 2.1
Name: routemaster-statsd
Version: 1.5.0
Summary: Statsd metrics reporting for Routemaster.
Home-page: https://github.com/thread/routemaster
Author: Thread
Author-email: tech@thread.com
License: MIT
Platform: UNKNOWN
Classifier: Development Status :: 2 - Pre-Alpha
Classifier: Environment :: Console
Classifier: Natural Language :: English
Classifier: Operating System :: POSIX
Classifier: Programming Language :: Python
Classifier: Programming Language :: Python :: 3 :: Only
Classifier: Programming Language :: Python :: 3.6
Classifier: Topic :: Office/Business
Requires-Dist: routemaster
Requires-Dist: statsd-python
